fast_markdown_mcp/__init__.py
fast_markdown_mcp/document_structure.py
fast_markdown_mcp/server.py
iflow_mcp_fast_markdown_mcp-0.1.0.dist-info/METADATA
iflow_mcp_fast_markdown_mcp-0.1.0.dist-info/WHEEL
iflow_mcp_fast_markdown_mcp-0.1.0.dist-info/entry_points.txt
iflow_mcp_fast_markdown_mcp-0.1.0.dist-info/RECORD
