Metadata-Version: 2.4
Name: iflow-mcp_fast-markdown-mcp
Version: 0.1.0
Summary: Fast MCP server for markdown content management with automatic file monitoring
Project-URL: Documentation, https://github.com/yourusername/fast-markdown-mcp#readme
Project-URL: Source, https://github.com/yourusername/fast-markdown-mcp
Author: CyberAGI Team
Requires-Python: >=3.10
Requires-Dist: anyio>=4.0.0
Requires-Dist: fastapi>=0.100.0
Requires-Dist: markdown>=3.4.0
Requires-Dist: mcp>=1.2.0
Requires-Dist: typing-extensions>=4.0.0
Requires-Dist: uvicorn>=0.30.0
Requires-Dist: watchdog>=3.0.0
